[
    {
        "editor_id": "ccBGSSSE034_MountUnicorn",
        "type": "NPC_ FULL",
        "original": "Unicorn",
        "string": "Unicornio"
    },
    {
        "editor_id": "ccBGSSSE034_WildHorse07_BrownSpotted",
        "type": "NPC_ FULL",
        "original": "Wild Horse",
        "string": "Caballo salvaje"
    },
    {
        "editor_id": "ccBGSSSE034_WildHorseMap",
        "type": "MISC FULL",
        "original": "Map of Wild Horses",
        "string": "Mapa de los caballos salvajes"
    },
    {
        "editor_id": "ccBGSSSE034_Misc_Horse05_RedBrown",
        "type": "QUST FULL",
        "original": "Find Horse 01",
        "string": "Encontrar al caballo 01"
    },
    {
        "editor_id": "ccBGSSSE034_WildHorse05_RedBrown",
        "type": "NPC_ FULL",
        "original": "Wild Horse",
        "string": "Caballo salvaje"
    },
    {
        "editor_id": "ccBGSSSE034_HorseLocationJournal",
        "type": "BOOK FULL",
        "original": "Wild Horse Notes",
        "string": "Notas sobre caballos salvajes"
    },
    {
        "editor_id": "ccBGSSSE034_HorseName20",
        "type": "MESG FULL",
        "original": "Lightning",
        "string": "Rayo"
    },
    {
        "editor_id": "ccBGSSSE034_HorseTameDamageStamina",
        "type": "MGEF FULL",
        "original": "Damage Stamina",
        "string": "Da\u00f1ar aguante"
    },
    {
        "editor_id": "ccBGSSSE034_HorseName24",
        "type": "MESG FULL",
        "original": "River",
        "string": "R\u00edo"
    },
    {
        "editor_id": "ccBGSSSE034_Misc_Horse02_Black",
        "type": "QUST FULL",
        "original": "Find Horse 02",
        "string": "Encontrar al caballo 02"
    },
    {
        "editor_id": "ccBGSSSE034_Misc_Horse05_RedBrown",
        "type": "QUST NNAM",
        "original": "Find and tame the Red Horse",
        "string": "Encuentra al caballo rojo y d\u00f3malo."
    },
    {
        "editor_id": "ccBGSSSE034_Misc_Horse02_Black",
        "type": "QUST NNAM",
        "original": "Find and tame the Black Horse",
        "string": "Encuentra al caballo negro y d\u00f3malo."
    },
    {
        "editor_id": "ccBGSSSE034_Misc_Horse01_Chestnut",
        "type": "QUST FULL",
        "original": "Find Horse 01",
        "string": "Encontrar al caballo 01"
    },
    {
        "editor_id": "ccBGSSSE034_WildHorse02_Black",
        "type": "NPC_ FULL",
        "original": "Wild Horse",
        "string": "Caballo salvaje"
    },
    {
        "editor_id": "ccBGSSSE034_HorseName21",
        "type": "MESG FULL",
        "original": "Dagger",
        "string": "Daga"
    },
    {
        "editor_id": "ccBGSSSE034_UnicornQuest",
        "type": "QUST NNAM",
        "original": "Find information about the Unicorn",
        "string": "Busca informaci\u00f3n sobre el unicornio."
    },
    {
        "editor_id": "ccBGSSSE034_HorseName25",
        "type": "MESG FULL",
        "original": "Glade",
        "string": "Claro"
    },
    {
        "editor_id": "ccBGSSSE034_HorseTameDamageStamina",
        "type": "MGEF DNAM",
        "original": "Drain the target's Stamina by <mag> points.",
        "string": "Consume <mag> puntos de aguante del objetivo."
    },
    {
        "editor_id": "ccBGSSSE034_UnicornQuest",
        "type": "QUST NNAM",
        "original": "Find and tame the Unicorn",
        "string": "Encuentra al unicornio y d\u00f3malo."
    },
    {
        "editor_id": "ccBGSSSE034_Misc_Horse07_BrownSpotted",
        "type": "QUST NNAM",
        "original": "Find and tame the Dapple Brown Horse",
        "string": "Encuentra al caballo marr\u00f3n con motas y d\u00f3malo."
    },
    {
        "editor_id": "ccBGSSSE034_WildHorse03_GreyBlack",
        "type": "NPC_ FULL",
        "original": "Wild Horse",
        "string": "Caballo salvaje"
    },
    {
        "editor_id": "ccBGSSSE034_Misc_Horse06_WhiteSpotted",
        "type": "QUST NNAM",
        "original": "Find and tame the White Spotted Horse",
        "string": "Encuentra al caballo blanco con manchas y d\u00f3malo."
    },
    {
        "editor_id": "ccBGSSSE034_WildHorse06_WhiteSpotted",
        "type": "NPC_ FULL",
        "original": "Wild Horse",
        "string": "Caballo salvaje"
    },
    {
        "editor_id": "ccBGSSSE034_PlayersHorseName",
        "type": "MESG FULL",
        "original": "<Alias=Player>'s Tamed Horse",
        "string": "Caballo domado de <Alias=Player>"
    },
    {
        "editor_id": "ccBGSSSE034_HelpWildHorseTutorial",
        "type": "MESG FULL",
        "original": "Wild Horse",
        "string": "Caballo salvaje"
    },
    {
        "editor_id": "ccBGSSSE034_Misc_Horse03_GreyBlack",
        "type": "QUST FULL",
        "original": "Find Horse 03",
        "string": "Encontrar al caballo 03"
    },
    {
        "editor_id": "ccBGSSSE034_HorseName19",
        "type": "MESG FULL",
        "original": "Thunder",
        "string": "Trueno"
    },
    {
        "editor_id": "ccBGSSSE034_UnicornSoransJournal",
        "type": "BOOK FULL",
        "original": "Soran's Journal",
        "string": "Diario de Soran"
    },
    {
        "editor_id": "ccBGSSSE034_WildHorsesQuest",
        "type": "QUST FULL",
        "original": "Horse Whisperer",
        "string": "Encantador de caballos"
    },
    {
        "editor_id": "ccBGSSSE034_Misc_Horse01_Chestnut",
        "type": "QUST NNAM",
        "original": "Find and tame the Chestnut Horse",
        "string": "Encuentra al caballo casta\u00f1o y d\u00f3malo."
    },
    {
        "editor_id": "ccBGSSSE034_WildHorse04_Pale",
        "type": "NPC_ FULL",
        "original": "Wild Horse",
        "string": "Caballo salvaje"
    },
    {
        "editor_id": "ccBGSSSE034_Misc_Horse04_Pale",
        "type": "QUST FULL",
        "original": "Find Horse 01",
        "string": "Encontrar al caballo 01"
    },
    {
        "editor_id": "ccBGSSSE034_WildHorsesQuest",
        "type": "QUST NNAM",
        "original": "Purchase a map of wild horse locations",
        "string": "Compra un mapa con las ubicaciones de los caballos salvajes."
    },
    {
        "editor_id": "ccBGSSSE034_Misc_Horse06_WhiteSpotted",
        "type": "QUST FULL",
        "original": "Find Horse 01",
        "string": "Encontrar al caballo 01"
    },
    {
        "editor_id": "ccBGSSSE034_Misc_Horse03_GreyBlack",
        "type": "QUST NNAM",
        "original": "Find and tame the Grey Spotted Horse",
        "string": "Encuentra al caballo gris con manchas y d\u00f3malo."
    },
    {
        "editor_id": "ccBGSSSE034_UnicornQuest",
        "type": "QUST FULL",
        "original": "Creature of Legend",
        "string": "Criatura de leyenda"
    },
    {
        "editor_id": "ccBGSSSE034_Misc_Horse04_Pale",
        "type": "QUST NNAM",
        "original": "Find and tame the Pale Mare",
        "string": "Encuentra a la yegua p\u00e1lida y d\u00f3mala."
    },
    {
        "editor_id": "ccBGSSSE034_WildHorse01_Chestnut",
        "type": "NPC_ FULL",
        "original": "Wild Horse",
        "string": "Caballo salvaje"
    },
    {
        "editor_id": "ccBGSSSE034_Misc_Horse07_BrownSpotted",
        "type": "QUST FULL",
        "original": "Find Horse 01",
        "string": "Encontrar al caballo 01"
    },
    {
        "editor_id": "ccBGSSSE034_HorseName23",
        "type": "MESG FULL",
        "original": "Whisper",
        "string": "Susurro"
    },
    {
        "editor_id": "ccBGSSSE034_HorseActivationPerk",
        "type": "PERK EPF2",
        "original": "Tame",
        "string": "Domar"
    },
    {
        "editor_id": "WinterholdCollegeArcanaeum",
        "type": "CELL FULL",
        "original": "The Arcanaeum",
        "string": "El arcaneum"
    },
    {
        "editor_id": "ccBGSSSE034_WildHorsesQuest",
        "type": "QUST CNAM",
        "original": "I've acquired a map and a journal with locations of where wild horses have been known to roam. I should find and tame them. Afterward I can bring them to a stable to add a saddle or change their name.",
        "string": "He conseguido un mapa y un diario con las ubicaciones conocidas de los caballos salvajes. Deber\u00eda buscarlos y domarlos. Despu\u00e9s podr\u00e9 llevarlos al establo para ponerles una silla de montar o cambiarles el nombre."
    },
    {
        "editor_id": "ccBGSSSE034_UnicornQuest",
        "type": "QUST CNAM",
        "original": "A wildlife scholar is rumored to have tracked down a legendary Unicorn. The last of these creatures was supposed to have been slain long ago. I should investigate and see what I can find.",
        "string": "Corre el rumor de que un investigador de criaturas ha localizado un unicornio legendario. Se supone que mataron al \u00faltimo ejemplar hace tiempo. Deber\u00eda investigarlo, a ver qu\u00e9 encuentro."
    },
    {
        "editor_id": "ccBGSSSE034_Misc_Horse06_WhiteSpotted",
        "type": "QUST CNAM",
        "original": "Find the horses.",
        "string": "Encuentra a los caballos."
    },
    {
        "editor_id": "ccBGSSSE034_UnicornSoransJournal",
        "type": "BOOK DESC",
        "original": "<font face=\"$HandwrittenFont\" size=\"18\">\nJournal of Soran Hariksen, Wildlife Scholar\n\n<b>14th of Rain's Hand, 4E 201</b>\nIn my duty to document all living creatures in Skyrim, the long-lost Unicorn has never been far from my mind. It is said that long ago the very last of its kind was sacrificed to Hircine. However, rumors of sightings in Tamriel have surfaced in recent times.\n\nIndeed, while these claims echo mostly from taverns in the late hours, one can wonder at the validity of such claims.\n\nI've chronicled the habits of Mudcrabs and Rabbits long enough. This old man is quite ready for something a little more interesting.\n\n<b>3rd of Second Seed, 4E 201</b>\nI have spoken with several hunters who swear by the Divines that they have seen a Unicorn during their travels. All have tried to approach it for a closer look, or to take it as a prize, but it has evaded them all.\n\nI continue my research with skepticism. If this is indeed true, how could this be? Was the last unicorn not truly the last, or is some other force at work?\n\n<b>18th of Second Seed, 4E 201</b>\nWhile studying the mating habits of Salmon is certainly enlightening, I have become quite obsessed with my pursuit of the elusive Unicorn.\n\nI spoke with a hostler who said that during one of his horse taming expeditions he too saw something that closely resembled the fabled Unicorn, though he was unsure. He is a man is of great integrity, so I took his word in good faith.\n\nI decided then to speak with Tolfdir at the College of Winterhold. Being a wise man with deep knowledge of such things, I hoped he might have some insight. I was correct in my assumption.\n\nAccording to Tolfdir, the Psijic Order have appeared from time-to-time throughout history to assist with situations they believe are extremely important. While he cannot personally say for certain, he believes they may have intervened after the last Unicorn was sacrificed, transporting another through time in order to set right what they believed was a wrongdoing.\n\nI am more motivated than ever to see this creature with my own two eyes.\n\n<b>24th of Second Seed, 4E 201</b>\nThe last sighting of the Unicorn was rumored to be in a dense forest area near Riften. As old as I am, an energy filled my bones that I haven't felt since I was a young man.\n\nI hiked up the ridge of the mountains there, and set up a very small camp. I was cautious to not set any fires or make much noise, lest I scare it away.\n\nAfter waiting two nights, through this morning's early fog, I finally saw the majestic creature for the first time. I still cannot believe my own two eyes. It lingered long enough for me to see it clearly, its brilliant coat and distinct horn shimmering in the morning light.\n\nI watched its movements for nearly thirty minutes, enough time to draw a rough depiction for my library. This is absolutely the crowning achievement of my scholarly life.\n\nI've decided to turn this information over to the College of Winterhold rather than publish it to the general population. I would like to ensure this creature remain protected, and I believe they are the most capable of such a task.",
        "string": "<font face=\"$HandwrittenFont\" size=\"18\">\nDiario de Soran Hariksen, investigador de criaturas\n\n<b>14 de Mano de lluvia, 201 de la Cuarta Era</b>\nEn mi labor de documentar todas las criaturas vivientes de Skyrim, el extinto unicornio siempre ha estado en mis pensamientos. Cuentan que el \u00faltimo ejemplar fue sacrificado en honor a Hircine hace tiempo. Sin embargo, \u00faltimamente han surgido rumores de avistamientos en Tamriel.\n\nAunque estos testimonios suelen dejarse o\u00edr en las tabernas bien avanzada la noche, no puedo dejar de preguntarme por la veracidad de esos rumores.\n\nYa llevo mucho tiempo registrando los h\u00e1bitos de los cangrejos del barro y los conejos. Este anciano est\u00e1 preparado para estudiar algo m\u00e1s interesante.\n\n<b>3 de Segunda semilla, 201 de la Cuarta Era</b>\nHe hablado con varios cazadores que juran por los Divinos haber visto un unicornio en sus expediciones. Todos intentaron acercarse para verlo m\u00e1s de cerca o para cobrarse la pieza y a todos les dio esquinazo.\n\nProsigo mi investigaci\u00f3n con escepticismo. Si los rumores son ciertos, \u00bfqu\u00e9 explicaci\u00f3n tienen? \u00bfEl \u00faltimo unicornio no era realmente el \u00faltimo? \u00bfLo atribuimos a una fuerza desconocida?\n\n<b>18 de Segunda semilla, 201 de la Cuarta Era</b>\nAunque estudiar los h\u00e1bitos de apareamiento de los salmones resulta enriquecedor, la b\u00fasqueda del esquivo unicornio sigue rob\u00e1ndome el sue\u00f1o.\n\nHe hablado con un mozo de cuadra que cre\u00eda haber visto algo mientras domaba caballos. Dec\u00eda que lo que vio encajaba con la descripci\u00f3n del legendario unicornio, aunque no parec\u00eda muy convencido. Se trata de un hombre de mucha integridad, as\u00ed que me f\u00edo de su palabra.\n\nDespu\u00e9s decid\u00ed ir al Colegio de Hibernalia para hablar con Tolfdir. Confiaba en que su vasta sabidur\u00eda en estas cosas arrojara algo de luz y no me equivoqu\u00e9.\n\nSeg\u00fan Tolfdir, la Orden Psijic ha aparecido en episodios concretos de la historia para ayudar en situaciones que consideraban de vital trascendencia. Aunque no puede afirmarlo a ciencia cierta, opina que es posible que intervinieran cuando el \u00faltimo unicornio fue sacrificado y que trajeran otro por el espacio-tiempo para enmendar lo que para ellos era un crimen.\n\nEstoy m\u00e1s ansioso que nunca por ver a esta criatura con mis propios ojos.\n\n<b>24 de Segunda semilla, 201 de la Cuarta Era</b>\nSe rumorea que vieron al unicornio por \u00faltima vez en una densa zona boscosa que hay cerca de Riften. Puede que sea un anciano, pero mis huesos rebosan de una energ\u00eda que no sent\u00eda desde mis a\u00f1os mozos.\n\nHe subido la cresta de las monta\u00f1as y he montado un peque\u00f1o campamento. He procurado no encender ninguna hoguera ni hacer ruido por temor a ahuyentarlo.\n\nPor fin. Despu\u00e9s de esperar dos noches, esta ma\u00f1ana he vislumbrado a la majestuosa criatura entre la niebla por primera vez. Mis ojos todav\u00eda no dan cr\u00e9dito. Estuvo quieto el tiempo suficiente para que yo pudiera ver con claridad su brillante pelaje y su caracter\u00edstico cuerno titilando con la luz matinal.\n\nEstuve observando sus movimientos durante casi media hora, suficiente para dibujar un boceto que puedo guardar para la posteridad. No cabe duda: este es el logro m\u00e1s importante de mi carrera como erudito.\n\nEn vez de divulgarlo por todo el mundo, he decidido transmitir este descubrimiento al Colegio de Hibernalia. Es mi deseo que esta criatura permanezca a salvo y creo que ellos son los m\u00e1s indicados para esa tarea."
    },
    {
        "editor_id": "ccBGSSSE034_MessageSaddleChanged",
        "type": "MESG DESC",
        "original": "Horse's saddle has been changed.",
        "string": "Le has cambiado la silla de montar al caballo."
    },
    {
        "editor_id": "ccBGSSSE034_MessageNotEnoughGold",
        "type": "MESG DESC",
        "original": "You do not have enough gold.",
        "string": "No tienes oro suficiente."
    },
    {
        "editor_id": "ccBGSSSE034_HorseLocationJournal",
        "type": "BOOK DESC",
        "original": "<font face=\"$HandwrittenFont\" size=\"18\">\nSpotted Grey - Near Markarth, north of Salvius Farm.\n\nDapple Brown - Near Solitude, across the river from Katla's Farm, near a Dragon Mound.\n\nChestnut - East of Helgen, not far from the roadside.\n\nRed - West of Whiterun, in the open planes.\n\nSpotted White - Lower Eastmarch, in the cliffs north of Shore's Stone.\n\nPale Mare - East of Windhelm, north of Hollyfrost Farm, in the forest nearing the shoreline.\n\nBlack - West of Falkreath, past the nearby ruins.\n\nIf I had the coin, I'd hire a wizard to use Detect Life and help me find these horses.\n</font>",
        "string": "<font face=\"$HandwrittenFont\" size=\"18\">\nGris con manchas: cerca de Markarth, al norte de la granja de Salvio.\n\nMarr\u00f3n con motas: cerca de Soledad, cruzando el r\u00edo desde la granja de Katla, junto a un t\u00famulo de drag\u00f3n.\n\nCasta\u00f1o: al este de Helgen, no muy lejos de la carretera.\n\nRojo: al oeste de Carrera Blanca, en campo abierto.\n\nBlanco con manchas: al sur de la Marca Oriental, en las colinas que hay al norte del Pe\u00f1\u00f3n de Shor.\n\nYegua p\u00e1lida: al este de Ventalia y al norte de la granja de Acebo Helado, en el bosque que hay junto a la costa.\n\nNegro: al oeste de Falkreath, pasadas las ruinas cercanas.\n\nSi tuviera dinero, contratar\u00eda a un hechicero para que usara Detectar vida y me ayudara a buscar estos caballos.\n</font>"
    },
    {
        "editor_id": "ccBGSSSE034_WildHorsesQuest",
        "type": "QUST CNAM",
        "original": "Hostlers in Skyrim have begun taming wild horses in order to keep up with the demand. I should speak with a hostler and see if they can give me some information. Perhaps I could find and tame some of them myself.",
        "string": "Los mozos de cuadra de Skyrim han empezado a domar caballos salvajes para satisfacer la demanda. Deber\u00eda hablar con alguno para ver si puede darme informaci\u00f3n. Tal vez pueda encontrar yo algunos y domarlos."
    },
    {
        "editor_id": "ccBGSSSE034_Misc_Horse04_Pale",
        "type": "QUST CNAM",
        "original": "Find the horses.",
        "string": "Encuentra a los caballos."
    },
    {
        "editor_id": "ccBGSSSE034_MessageNoHorsesOwned",
        "type": "MESG DESC",
        "original": "You do not currently own a horse.",
        "string": "En este momento no tienes ning\u00fan caballo."
    },
    {
        "editor_id": "ccBGSSSE034_MessageCantChangeSaddle",
        "type": "MESG DESC",
        "original": "Current horse cannot have its saddle changed.",
        "string": "No le puedes cambiar la silla de montar al caballo actual."
    },
    {
        "editor_id": "ccBGSSSE034_UnicornQuest",
        "type": "QUST CNAM",
        "original": "I found the journal of wildlife scholar Soran Hariksen at the College of Winterhold, which contained details on the whereabouts of the Unicorn. I should locate it to see if I can tame it, and take care of it as my own.",
        "string": "He encontrado el diario del erudito Soran Hariksen en el Colegio de Hibernalia. Conten\u00eda informaci\u00f3n sobre el paradero del unicornio. Deber\u00eda buscarlo para ver si puedo domarlo y cuidarlo como si fuera m\u00edo."
    },
    {
        "editor_id": "ccBGSSSE034_MessageNameChanged",
        "type": "MESG DESC",
        "original": "Horse has been renamed.",
        "string": "Has rebautizado al caballo."
    },
    {
        "editor_id": "ccBGSSSE034_Misc_Horse05_RedBrown",
        "type": "QUST CNAM",
        "original": "Find the horses.",
        "string": "Encuentra a los caballos."
    },
    {
        "editor_id": "ccBGSSSE034_Misc_Horse01_Chestnut",
        "type": "QUST CNAM",
        "original": "Find the horse.",
        "string": "Encuentra al caballo."
    },
    {
        "editor_id": "ccBGSSSE034_Misc_Horse07_BrownSpotted",
        "type": "QUST CNAM",
        "original": "Find the horses.",
        "string": "Encuentra a los caballos."
    },
    {
        "editor_id": "ccBGSSSE034_HelpWildHorseTutorial",
        "type": "MESG DESC",
        "original": "Wild horses will buck until tamed. Stay mounted until they submit. If you are thrown, try again. Once tamed, you can add a saddle and rename them at any stable.\n\nWhen changing horses, tamed horses will return to the location where they were found.",
        "string": "Los caballos salvajes se encabritar\u00e1n hasta que los domes. Qu\u00e9date encima de ellos hasta que se rindan. Si te tiran, vuelve a intentarlo. Cuando los domes, podr\u00e1s ponerles una silla de montar y cambiarles el nombre en cualquier establo.\n\nSi cambias de caballo, los que est\u00e9n domados volver\u00e1n al lugar donde los encontraste."
    },
    {
        "editor_id": "ccBGSSSE034_MessageSaddleRemoved",
        "type": "MESG DESC",
        "original": "Horse's saddle has been removed.",
        "string": "Le has quitado la silla de montar al caballo."
    },
    {
        "editor_id": "ccBGSSSE034_WildHorseMessageTamed",
        "type": "MESG DESC",
        "original": "Horse has been successfully tamed.",
        "string": "Has domado al caballo."
    },
    {
        "editor_id": "ccBGSSSE034_HorseTameSpellDrainStamina",
        "type": "SPEL DESC",
        "original": "Raises all dead around you to fight for you.",
        "string": "Reanima a los muertos que tengas cerca para que luchen por ti."
    },
    {
        "editor_id": "ccBGSSSE034_Misc_Horse03_GreyBlack",
        "type": "QUST CNAM",
        "original": "Find the horses.",
        "string": "Encuentra a los caballos."
    },
    {
        "editor_id": "ccBGSSSE034_Misc_Horse02_Black",
        "type": "QUST CNAM",
        "original": "Find the horses.",
        "string": "Encuentra a los caballos."
    },
    {
        "editor_id": "ccBGSSSE034_UnicornQuest",
        "type": "QUST CNAM",
        "original": "A wildlife scholar was able to track down and verify the existence of a Unicorn. Using information that I found in his journal, I located the Unicorn, tamed it, and claimed it as my own. If I need to find it again, it will be at the College of Winterhold courtyard.",
        "string": "Un investigador de criaturas ha logrado rastrear y confirmar la existencia de un unicornio. Gracias a la informaci\u00f3n de su diario, localic\u00e9 al unicornio, lo dom\u00e9 y lo hice m\u00edo. Si quiero volver a verlo, lo encontrar\u00e9 en el patio del Colegio de Hibernalia."
    },
    {
        "editor_id": "ccBGSSSE034_MessageMustBeTamedRename",
        "type": "MESG DESC",
        "original": "Horse must be tamed to change its name.",
        "string": "Debes domar al caballo para cambiarle el nombre."
    },
    {
        "editor_id": "ccBGSSSE034_MessageMustBeTamedSaddle",
        "type": "MESG DESC",
        "original": "Horse must be tamed to change saddles.",
        "string": "Debes domar al caballo para cambiar la silla de montar."
    }
]