[{"original": "Ghost Death FX", "form_id": "05000811|ccvsvsse004-beafarmer.esl", "type": "MGEF FULL", "editor_id": "ccVSVSSE004_MGEF_GhostDeath", "string": "Ghost Death FX"}, {"original": "Ghost Death FX", "form_id": "05000812|ccvsvsse004-beafarmer.esl", "type": "SPEL FULL", "editor_id": "ccVSVSSE004_AB_GhostDeathFX", "string": "Ghost Death FX"}, {"original": "Rin's Sword", "form_id": "05000813|ccvsvsse004-beafarmer.esl", "type": "ACTI FULL", "editor_id": "ccVSVSSE004_ACT_ToySwordTrigger", "string": "Меч Рина"}, {"original": "Place", "form_id": "05000813|ccvsvsse004-beafarmer.esl", "type": "ACTI RNAM", "editor_id": "ccVSVSSE004_ACT_ToySwordTrigger", "string": "Положить"}, {"original": "Shrine", "form_id": "0500086D|ccvsvsse004-beafarmer.esl", "type": "ACTI FULL", "editor_id": "ccVSVSSE004_ACT_ShrineChoose", "string": "Святилище"}, {"original": "Choose", "form_id": "0500086D|ccvsvsse004-beafarmer.esl", "type": "ACTI RNAM", "editor_id": "ccVSVSSE004_ACT_ShrineChoose", "string": "Выбрать"}, {"original": "Fertile Soil", "form_id": "0500086E|ccvsvsse004-beafarmer.esl", "type": "ACTI FULL", "editor_id": "ccVSVSSE004_ACT_PlanterSoil", "string": "Плодородная земля"}, {"original": "Blacksmithing Workshop", "form_id": "05000872|ccvsvsse004-beafarmer.esl", "type": "ARMO FULL", "editor_id": "ccVSVSSE004_ExtFeat_CraftingArea", "string": "Кузнечная мастерская"}, {"original": "Builds a blacksmithing workshop. Includes an anvil, grindstone, armor workbench, tanning rack, and smelter. ", "form_id": "05000872|ccvsvsse004-beafarmer.esl", "type": "ARMO DESC", "editor_id": "ccVSVSSE004_ExtFeat_CraftingArea", "string": "Строит мастерскую с наковальней, точильным камнем, верстаком бронника, дубильным станком и плавильней. "}, {"original": "Exterior Decoration", "form_id": "05000873|ccvsvsse004-beafarmer.esl", "type": "ARMO FULL", "editor_id": "ccVSVSSE004_ExtFeat_ExtDeco", "string": "Наружные украшения"}, {"original": "Builds a well and planter boxes. Also adds exterior furniture and decorations to the farmhouse.", "form_id": "05000873|ccvsvsse004-beafarmer.esl", "type": "ARMO DESC", "editor_id": "ccVSVSSE004_ExtFeat_ExtDeco", "string": "Строительство колодца и клумб, а также наружной мебели и украшений для фермерского дома."}, {"original": "Windmill", "form_id": "05000875|ccvsvsse004-beafarmer.esl", "type": "ARMO FULL", "editor_id": "ccVSVSSE004_ExtFeat_Windmill", "string": "Ветряная мельница"}, {"original": "Upgrades the silo into a windmill and adds a grain mill for turning wheat into flour or straw.", "form_id": "05000875|ccvsvsse004-beafarmer.esl", "type": "ARMO DESC", "editor_id": "ccVSVSSE004_ExtFeat_Windmill", "string": "Превращение амбара в ветряную мельницу, позволяющую перерабатывать пшеницу в муку или солому."}, {"original": "Stable", "form_id": "05000874|ccvsvsse004-beafarmer.esl", "type": "ARMO FULL", "editor_id": "ccVSVSSE004_ExtFeat_Stable", "string": "Стойло"}, {"original": "Builds a stable. Allows a horse to be purchased for the farm. ", "form_id": "05000874|ccvsvsse004-beafarmer.esl", "type": "ARMO DESC", "editor_id": "ccVSVSSE004_ExtFeat_Stable", "string": "Строительство стойла, которое позволит купить лошадь для фермы. "}, {"original": "Animal Pens", "form_id": "0500086F|ccvsvsse004-beafarmer.esl", "type": "ARMO FULL", "editor_id": "ccVSVSSE004_ExtFeat_AnimalPen", "string": "Загоны для скота"}, {"original": "Builds animal pens. Allows cows, goats, and chickens to be purchased for the farm. ", "form_id": "0500086F|ccvsvsse004-beafarmer.esl", "type": "ARMO DESC", "editor_id": "ccVSVSSE004_ExtFeat_AnimalPen", "string": "Строительство загонов для скота, которые позволят купить коров, коз и кур для фермы. "}, {"original": "Apiary", "form_id": "05000870|ccvsvsse004-beafarmer.esl", "type": "ARMO FULL", "editor_id": "ccVSVSSE004_ExtFeat_Apiary", "string": "Улей"}, {"original": "Builds 2 apiaries that produce bees, honeycomb, and honey. ", "form_id": "05000870|ccvsvsse004-beafarmer.esl", "type": "ARMO DESC", "editor_id": "ccVSVSSE004_ExtFeat_Apiary", "string": "Строительство двух ульев, производящих пчел, соты и мед. "}, {"original": "Farmhand Bunkhouse", "form_id": "05000871|ccvsvsse004-beafarmer.esl", "type": "ARMO FULL", "editor_id": "ccVSVSSE004_ExtFeat_Bunkhouse", "string": "Ночлежка"}, {"original": "Builds a cottage for your hired help. Increases the productivity of the farm. ", "form_id": "05000871|ccvsvsse004-beafarmer.esl", "type": "ARMO DESC", "editor_id": "ccVSVSSE004_ExtFeat_Bunkhouse", "string": "Строительство ночлежки для наемных работников фермы, повышающей производительность их труда. "}, {"original": "Bounty - Restless Spirits", "form_id": "05000815|ccvsvsse004-beafarmer.esl", "type": "BOOK FULL", "editor_id": "ccVSVSSE004_BOOK_BountyHauntedFarm", "string": "Заказ: неупокоенные духи"}, {"original": "<font face=\"$HandwrittenFont\">\r\n<font size=\"40\">Bounty</font>\r\n\r\nBy order of <Alias=Jarl>:\r\n\r\nTo all able bodied and fearless men and women of Whiterun Hold. Travelers on the road near <Alias=FarmLocation> are being terrorized by ghosts haunting the nearby farm. \r\n\r\nAnyone who is able to banish the ghosts permanently will be rewarded with the land rights to <Alias=FarmLocation>.\r\n\r\n--<Alias=Steward>", "form_id": "05000815|ccvsvsse004-beafarmer.esl", "type": "BOOK DESC", "editor_id": "ccVSVSSE004_BOOK_BountyHauntedFarm", "string": "<font face=\"$HandwrittenFont\">\r\n<font size=\"40\">Заказ</font>\r\n\r\n<Alias=Jarl> повелевает:\r\n\r\nВсем сильным и бесстрашным мужам и женам Вайтрана. <Alias=FarmLocation> становится опасным местом: я все чаще получаю сообщения о призраках, которые обитают на местной ферме и нападают на путников. \r\n\r\nЕсли кто-либо сумеет навсегда изгнать этих потусторонних тварей, <Alias=FarmLocation> перейдет в его пожизненную собственность.\r\n\r\n--<Alias=Steward>"}, {"original": "<Alias=Wife>'s Journal", "form_id": "05000816|ccvsvsse004-beafarmer.esl", "type": "BOOK FULL", "editor_id": "ccVSVSSE004_BOOK_JournalWife", "string": "Дневник: <Alias=Wife>"}, {"original": "<font face=\"$HandwrittenFont\"><b>23th of First Seed</b>\r\n\r\n<Alias=Husband> wanted so badly to make a go at being farmers, so here we are now with our own rocky plot of land and a ruined old farmhouse with a leaky roof. It's not what I dreamed of, but we'll make the best of it. \r\n\r\nAt least the soil's good, even if it's full of boulders. I'll be able to get a nice garden going, with all the ingredients I need for my potions. The income from that should get us through the first winter, if nothing else. \r\n[pagebreak]\r\n<b>10th of Second Seed</b>\r\n\r\nI found a secret room walled off in the basement. It will do nicely for my alchemy lab; I love my husband dearly, but he can be a pig-headed dolt when it comes to the gentle magics of the earth. If it weren't for my potions, little <Alias=GhostChild> would have perished last winter from a fever. \r\n[pagebreak]\r\n<b>1st of Frostfall</b>\r\n\r\nOur plantation is doing well enough, but <Alias=Husband>'s eyes are getting bigger than his purse. He was talking of purchasing a wagon recently, like we don't sometimes struggle to put food on the table. A wagon, honestly! \r\n\r\nI've seen the ugly looks he gives my potions and herbs, but where else are we going to get the money for all the things he buys? Next thing you know, he'll be trying to buy another farm!\r\n[pagebreak]\r\n<b>13th of Mid Year</b>\r\n\r\n<Alias=GhostChild>'s gone missing. We've looked everywhere, but we can't find find him. His little wooden sword is missing too - gods perserve me, I hope he hasn't run off! He doesn't realize how dangerous it is out there on the tundra. \r\n[pagebreak]\r\n<b>16th of Mid Year</b>\r\n\r\nIt's been three days now. My little boy is still gone. I don't like how <Alias=Husband> is looking at me - his eyes are too dark, too still, like a frozen lake. I think I even heard him mutter something about \"getting what I deserve.\" \r\n\r\nCould he have...? No, I dare not even put the thought to paper. \r\n[pagebreak]\r\nHe did it. He must have. That monster killed my son, and now he looks at me with those hate-filled eyes and a mocking smirk. He despises my alchemical arts so much that he took my son from me to punish me. \r\n\r\nI've never brewed poison before, but I know how it's done. I know how to bottle death. A few drops in his mead and my child will be avenged.\r\n[pagebreak]\r\nIt is done. The gods will damn me, but they will damn him more for the murder of a child. <Alias=GhostChild>, I'm so sorry. I wish I could have-\r\n\r\nWait, I hear someth\r\n</font>\r\n", "form_id": "05000816|ccvsvsse004-beafarmer.esl", "type": "BOOK DESC", "editor_id": "ccVSVSSE004_BOOK_JournalWife", "string": "<font face=\"$HandwrittenFont\"><b>23-е Первого зерна</b>\r\n\r\n<Alias=Husband> давно мечтал стать фермером. Его мечта сбылась: теперь у нас есть собственный клочок каменистой земли и старая развалюха с дырявой крышей. Я представляла себе все совсем не так, ну да ладно. Будем работать с тем, что есть.\r\n\r\nПочва здесь плодородная, хоть и каменистая. На ней можно устроить неплохой садик для выращивания всех необходимых ингредиентов. Доход от моих зелий как минимум поможет нам продержаться первую зиму. \r\n[pagebreak]\r\n<b>10-е Второго зерна</b>\r\n\r\nВ подвале дома я нашла тайную комнату, самой судьбой предназначенную для алхимии. Я очень люблю своего мужа, но он приходит в бешенство, едва заслышав о моей скромной магии земли. Между прочим, если бы не мои зелья, наш <Alias=GhostChild> прошлой зимой умер бы от лихорадки. \r\n[pagebreak]\r\n<b>1-е Начала морозов</b>\r\n\r\nДела на ферме идут неплохо, но не настолько хорошо, как думает <Alias=Husband>. Недавно он решил купить телегу - и это при том, что нам не всегда хватает денег на еду. Честное слово, телегу! \r\n\r\nЯ прекрасно знаю, как он относится к моим зельям и травкам, но если бы не одни, где бы мы взяли деньги на все его траты? Если так пойдет и дальше, он захочет купить еще одну ферму!\r\n[pagebreak]\r\n<b>13-е Середины года</b>\r\n\r\n<Alias=GhostChild> куда-то пропал. Мы искали его повсюду, но так и не нашли. Его деревянный меч тоже исчез. Храни меня боги, надеюсь, он не сбежал! Он же не понимает, насколько опасно в тундре. \r\n[pagebreak]\r\n<b>16-е Середины года</b>\r\n\r\nПрошло уже три дня. Малыш так и не нашелся. И мне не нравится, как <Alias=Husband> смотрит на меня. Его взгляд слишком хмурый и неподвижный, как ледяное озеро. Кажется, иногда он даже бормочет что-то вроде \"получила по заслугам\"\". \r\n\r\nМожет быть, он?... Нет, боюсь даже писать об этом. \r\n[pagebreak]\r\nЭто сделал он. Я уверена. Этот монстр убил моего сына, а теперь бросает на меня взгляды, полные злобы и насмешки. Он так ненавидит мое алхимическое искусство, что убил собственного сына ради того, чтобы досадить мне. \r\n\r\nЯ никогда не готовила такие зелья, но отлично знаю их рецепты. Я читала о ядах. Пара капель в мед - и мой сын будет отомщен.\r\n[pagebreak]\r\nВот и все. Пусть боги меня проклянут, но этого убийцу они проклянут еще больше. <Alias=GhostChild>, прости меня. Если бы я могла...\r\n\r\nСтоп, кажется, я что-то слы...\r\n</font>\r\n"}, {"original": "<Alias=Husband>'s Journal", "form_id": "05000817|ccvsvsse004-beafarmer.esl", "type": "BOOK FULL", "editor_id": "ccVSVSSE004_BOOK_JournalHusband", "string": "Дневник: <Alias=Husband>"}, {"original": "<font face=\"$HandwrittenFont\"><b>14th of First Seed</b>\r\n\r\nToday's the first day of our new lives. I bought a sizable piece of land with a run-down farmhouse for dirt cheap just outside of Rorikstead. No one else wanted it, on account of how rocky it is. Too many boulders, the other men said. But <Alias=Wife> and I have strong backs and willing hearts; we'll get those boulders out, and turn this fertile land into a plantation they could only dream of. \r\n\r\nThis will be the perfect place to raise our little <Alias=GhostChild>.\r\n[pagebreak]\r\n<b>21st of Second Seed</b>\r\n\r\nLong day. Hand hurts almost too much to write. Farmhouse is repaired, and the first plants are in the ground. Feels good. We did it. <Alias=Wife> kissed me tonight like she did when we were first married. Her eyes are calling me. \r\n[pagebreak]\r\n<b>1st of Sun's Height</b>\r\n\r\nWe harvested our first crops today. It wasn't much, but it's a start. When I watched the sun's rays first break over the horizon on our fields today, I knew what to name this place - <Alias=FarmLocation>, after Akatosh's glorious light. Soon, it will be an inheritence worthy of our son. Just a bit longer, I know it.\r\n[pagebreak]\r\n<b>23rd of Frostfall</b>\r\n\r\nMy heart is troubled. <Alias=GhostChild> is fast growing into a strapping young boy, though he spends too much time playing with that wooden sword of his and dreaming of running off to join the Legion. \r\n\r\nBut my dear wife, <Alias=Wife>... her strangeness worries me. Sometimes she'll disappear for hours at a time, and then turn up in the house as though she'd been there all along. I often see her carrying a basket full of strange dark flowers, and she won't tell me what they are or where she got them. And last winter, when <Alias=GhostChild> fell ill with fever, <Alias=Wife> produced a small black bottle from who knows where and poured who knows what down his throat... only a few minutes later, the fever was gone. <Alias=Wife> refused to tell me what was in the bottle, or where she got it. I was so happy that she saved our little boy, of course, but...\r\n\r\nMara preserve me, but I'm afraid that my wife is a daedra worshipper, or a witch.\r\n[pagebreak]\r\n<b>16th of Mid Year</b>\r\n\r\n<Alias=GhostChild> has been missing for three days. My little boy.\r\n\r\nI've searched everywhere, but there's no trace of him. Even his favorite toy sword is missing. What if wolves got him? Or brigands snatched him away? \r\n\r\n<Alias=Wife> has been watching me. I don't like the look in her eyes. And she hasn't cried at all. What kind of mother doesn't cry when her child is missing? \r\n\r\nWhat if-\r\nI dare not even put the thought to paper. It's unthinkable. \r\n[pagebreak]\r\nI found it. I found <Alias=Wife>'s secret. This is the place she's been disappearing to. The potions, the plants, the books... such evil and unnatural things I found down there. Divines help me, my wife is a witch.\r\n\r\nI didn't want to open her foul books, but I had to know, I had to-\r\n\r\nDeadly Nightshade. That's what the plant is called, the one I saw her sneaking around with. She grows it everywhere in this hidden place.\r\n\r\nShe must have poisoned my son. I've seen the sneer on her face, the laughter in her eyes as she watched me tearing apart the farm looking for him. She was mocking me. \r\n\r\nI've never felt rage like this. I'm shaking with it, sweating with it. \r\nI know exactly what I've got to do. My son's spirit whispers to me, demanding vengeance. \r\n\r\nI keep an axe by the door for dealing with wild animals. It will do for dealing with a witch as well. \r\n</font>", "form_id": "05000817|ccvsvsse004-beafarmer.esl", "type": "BOOK DESC", "editor_id": "ccVSVSSE004_BOOK_JournalHusband", "string": "<font face=\"$HandwrittenFont\"><b>14-е Первого зерна</b>\r\n\r\nСегодня первый день нашей новой жизни. Я приобрел внушительный кусок земли со старой хибарой возле Рорикстеда. Он достался мне очень дешево: из-за обилия валунов его никто не хотел покупать. Но я упорный, как и моя <Alias=Wife>. Мы уберем все камни и устроим на местных плодородных почвах сказочно богатую ферму. \r\n\r\nК тому же, в новом поместье наш маленький <Alias=GhostChild> сможет вырасти сильным и здоровым.\r\n[pagebreak]\r\n<b>21-е Второго зерна</b>\r\n\r\nКакой длинный день. Руки болят так, что трудно писать. Дом отремонтирован, первые растения посажены. Это хорошо. Мы справились. Сегодня <Alias=Wife> целовала меня так же, как в первую брачную ночь. Ее глаза блестели. \r\n[pagebreak]\r\n<b>1-е Высокого солнца</b>\r\n\r\nСегодня мы собрали свой первый урожай. Небольшой, но ведь это только начало. Глядя на рассвете, как первые солнечные лучи озаряют наши поля, я придумал название для этого поместья: <Alias=FarmLocation> - в честь сияния славы Акатоша. Эта земля станет достойным наследством для нашего сына. Надо только немного потрудиться.\r\n[pagebreak]\r\n<b>23-е Начала морозов</b>\r\n\r\nМне тревожно. <Alias=GhostChild> в полном порядке. Он стал крепким подростком, хотя и проводит все время с деревянным мечом, мечтая сбежать в Легион. \r\n\r\nА вот <Alias=Wife>, моя дражайшая супруга... ведет себя странно. Иногда она исчезает на долгие часы, а потом снова появляется, как ни в чем не бывало. Я часто вижу у нее в руках корзины с какими-то странными темными цветами, о которых она отказывается говорить. А прошлой зимой, когда <Alias=GhostChild> свалился с лихорадкой, <Alias=Wife> достала маленькую черную бутылочку с какой-то дрянью и вылила ее содержимое ему в рот... и через несколько минут лихорадка прошла. <Alias=Wife> так и не сказала мне, что было в той бутылочке и откуда она ее взяла. Здорово, конечно, что она вылечила нашего малыша, но...\r\n\r\nХрани меня Мара, но я боюсь, что моя жена - ведьма или прислужница даэдра.\r\n[pagebreak]\r\n<b>16-е Середины года</b>\r\n\r\n<Alias=GhostChild> пропал. Его нет уже третий день.\r\n\r\nЯ искал его повсюду, но не нашел никаких следов. Даже его любимый игрушечный меч куда-то исчез. Неужели его съели волки или утащили разбойники? \r\n\r\n<Alias=Wife> следит за мной. Мне не нравится ее взгляд, в котором нет ни единой слезинки. Что это за мать, которая не плачет, потеряв сына? \r\n\r\nА вдруг...\r\nНет, боюсь даже писать об этом. Такого просто не может быть. \r\n[pagebreak]\r\nЯ все знаю. Я знаю, какую тайну скрывала <Alias=Wife>. Я нашел место, куда она исчезает. Зелья, травы, книги... сколько всего чуждого и злодейского она там прячет. Храни меня боги. Моя жена - ведьма.\r\n\r\nЯ не хотел открывать ее нечестивые книги, но я должен был узнать. Я должен был...\r\n\r\nЯдовитый паслен. Вот как называются эти странные цветы, которые я у нее видел. Она выращивает их в своем зловещем логове.\r\n\r\nВидимо, она и отравила сына. Глядя, как я в отчаянии прочесываю ферму, она коварно улыбалась, а в ее глазах был смех. Она смеялась надо мной. \r\n\r\nТакого гнева я не испытывал никогда в жизни. Он разрывает меня изнутри и пробивает холодным потом. \r\nЯ точно знаю, что должен сделать. Дух сына молит меня о мести. \r\n\r\nВозле двери есть топор на случай нападения диких зверей. Надеюсь, он поможет и против ведьмы. \r\n</font>"}, {"original": "Rin's Journal", "form_id": "05000818|ccvsvsse004-beafarmer.esl", "type": "BOOK FULL", "editor_id": "ccVSVSSE004_BOOK_JournalChild", "string": "Дневник Рина"}, {"original": "<font face=\"$HandwrittenFont\">\r\n\r\nMa and Pa are fighting again. They're always fighting these days. Ma hates how obsessed Pa is with cows and the price of wheat, and all that boring stuff. Pa doesn't like Ma's flowers or her bottles of goopy stuff. I don't like the goopy stuff either, but it does make me feel better when I'm sick, so I guess it's okay. \r\n\r\nI can't wait till I'm old enough to join the Legion and get away from the farm. I've been practicing every day with my sword - I think I'm good enough to be a captain, or even a general! But Pa doesn't want me to join the Legion cause he says I have to take over the farm when I'm old enough. Ma doesn't want me to go cause it's dangerous. That's about the only thing they agree on.\r\n\r\nI bet if I defeated a bandit or killed a wolf or something that would show them! Then they would have to let me join up with the Legion. \r\n\r\nPa always tells me to stay away from the old well, the one toward the tall monument, out by the tree sitting on a rock. Wolves like to hunt out there, he says. So that's where I'll go. I'll kill a wolf and bring home its head, and that'll prove I'm a man and not a baby.\r\n\r\nI'm tired of listening to Ma and Pa yell at each other anyway.\r\n\r\n</font>\r\n", "form_id": "05000818|ccvsvsse004-beafarmer.esl", "type": "BOOK DESC", "editor_id": "ccVSVSSE004_BOOK_JournalChild", "string": "<font face=\"$HandwrittenFont\">\r\n\r\nМама с папой опять поссорились. Они все время ссорятся. Мама говорит, что папа совсем рехнулся со своими коровами, ценами на зерно и прочей скучной ерундой. Папе не нравится, что мама возится с травками, склянками и вонючей слизью. Мне тоже не нравится вонючая слизь, но когда я болею, от нее становится легче. Значит, она полезная. \r\n\r\nЯ очень хочу поскорее стать взрослым, поступить в Легион и уйти с этой фермы. Я каждый день тренируюсь с мечом. Думаю, у меня получится стать капитаном, а может быть, даже генералом! Но папа не хочет меня отпускать: он говорит, что я должен унаследовать его ферму. Мама тоже не хочет, потому что это опасно. Хоть в чем-то они согласны.\r\n\r\nВот если бы я победил разбойника или, скажем, волка, они бы точно в меня поверили! И наверняка отпустили бы служить. \r\n\r\nПапа запрещает ходить к старому колодцу возле высокого памятника, что у дерева на скале. Он говорит, что там водятся волки. Туда я и пойду. Я убью волка, принесу домой его голову и докажу всем, что я уже не маленький!\r\n\r\nЭто всяко интереснее, чем слушать вечную ругань мамы с папой.\r\n\r\n</font>\r\n"}, {"original": "Torn Page", "form_id": "05000F34|ccvsvsse004-beafarmer.esl", "type": "BOOK FULL", "editor_id": "ccVSVSSE004_BOOK_JournalHusband_note", "string": "Вырванная страница"}, {"original": "<font face=\"$HandwrittenFont\">\r\n<i>\r\nI feel...strange. Hot and cold all at once. My hand shakes. Hard to write. So dizzy...\r\nI think I've been poisoned...\r\n\r\nSeems she got the better of me after all...\r\n</i>\r\n</font>", "form_id": "05000F34|ccvsvsse004-beafarmer.esl", "type": "BOOK DESC", "editor_id": "ccVSVSSE004_BOOK_JournalHusband_note", "string": "<font face=\"$HandwrittenFont\">\r\n<i>\r\nМне... странно. Холодно и жарко сразу. Руки дрожат. Трудно писать. Голова кружится...\r\nПохоже на отравление...\r\n\r\nКажется, она меня все-таки сделала...\r\n</i>\r\n</font>"}, {"original": "Chest", "form_id": "05000819|ccvsvsse004-beafarmer.esl", "type": "CONT FULL", "editor_id": "ccVSVSSE004_CONT_ChestCommonEmpty_noRespawn", "string": "Сундук"}, {"original": "Chest", "form_id": "0500081A|ccvsvsse004-beafarmer.esl", "type": "CONT FULL", "editor_id": "ccVSVSSE004_QAChest", "string": "Сундук"}, {"original": "End Table", "form_id": "0500081B|ccvsvsse004-beafarmer.esl", "type": "CONT FULL", "editor_id": "ccVSVSSE004_CONT_FancyEndTable", "string": "Тумбочка"}, {"original": "Pantry Cupboard", "form_id": "05000876|ccvsvsse004-beafarmer.esl", "type": "CONT FULL", "editor_id": "ccVSVSSE004_CONT_PantryCupboard", "string": "Буфет для кладовой"}, {"original": "Wardrobe", "form_id": "05000877|ccvsvsse004-beafarmer.esl", "type": "CONT FULL", "editor_id": "ccVSVSSE004_CONT_FancyWardrobe", "string": "Шкаф"}, {"original": "End Table", "form_id": "05000878|ccvsvsse004-beafarmer.esl", "type": "CONT FULL", "editor_id": "ccVSVSSE004_CONT_CommonEndTableLong", "string": "Тумбочка"}, {"original": "Apiary", "form_id": "05000879|ccvsvsse004-beafarmer.esl", "type": "CONT FULL", "editor_id": "ccVSVSSE004_CONT_Apiary", "string": "Улей"}, {"original": "Wooden Door", "form_id": "02015484|Dawnguard.esm", "type": "DOOR FULL", "editor_id": "ccVSVSSE004_BunkerFarmhouseLDoor01", "string": "Деревянная дверь"}, {"original": "Wooden Door", "form_id": "02015479|Dawnguard.esm", "type": "DOOR FULL", "editor_id": "ccVSVSSE004_MainFarmhouseLDoor01", "string": "Деревянная дверь"}, {"original": "Wooden Door", "form_id": "0201547B|Dawnguard.esm", "type": "DOOR FULL", "editor_id": "ccVSVSSE004_BalconyFarmhouseLDoor01", "string": "Деревянная дверь"}, {"original": "Alembic", "form_id": "0500082A|ccvsvsse004-beafarmer.esl", "type": "MISC FULL", "editor_id": "ccVSVSSE004_MISC_Alembic", "string": "Перегонный куб"}, {"original": "Bed", "form_id": "0500084E|ccvsvsse004-beafarmer.esl", "type": "FURN FULL", "editor_id": "ccVSVSSE004_FURN_FancyBedChild01R", "string": "Кровать"}, {"original": "Butter Churn", "form_id": "0500084F|ccvsvsse004-beafarmer.esl", "type": "FURN FULL", "editor_id": "ccVSVSSE004_FURN_ButterChurn", "string": "Маслобойка"}, {"original": "Grain Mill", "form_id": "05000851|ccvsvsse004-beafarmer.esl", "type": "FURN FULL", "editor_id": "ccVSVSSE004_FURN_GrainMill", "string": "Зерновая мельница"}, {"original": "Farmer's Workbench", "form_id": "05000852|ccvsvsse004-beafarmer.esl", "type": "FURN FULL", "editor_id": "ccVSVSSE004_FRUN_Workbench_ext", "string": "Фермерский верстак"}, {"original": "Bed", "form_id": "0500084C|ccvsvsse004-beafarmer.esl", "type": "FURN FULL", "editor_id": "ccVSVSSE004_FURN_FancyBedDouble", "string": "Кровать"}, {"original": "Bed", "form_id": "0500084D|ccvsvsse004-beafarmer.esl", "type": "FURN FULL", "editor_id": "ccVSVSSE004_FURN_FancyBedChild01L", "string": "Кровать"}, {"original": "Wooden Sword", "form_id": "05000854|ccvsvsse004-beafarmer.esl", "type": "WEAP FULL", "editor_id": "ccVSVSSE004_WPN_ToySword", "string": "Деревянный меч"}, {"original": "Ghost", "form_id": "0500085B|ccvsvsse004-beafarmer.esl", "type": "NPC_ FULL", "editor_id": "ccVSVSSE004_GhostHusband_peaceful", "string": "Призрак"}, {"original": "Planter", "form_id": "05000888|ccvsvsse004-beafarmer.esl", "type": "NPC_ FULL", "editor_id": "ccVSVSSE004_FarmPlanterNPC", "string": "Цветочник"}, {"original": "Farmhand", "form_id": "05000889|ccvsvsse004-beafarmer.esl", "type": "NPC_ FULL", "editor_id": "ccVSVSSE004_Farmhand__Template", "string": "Работник фермы"}, {"original": "Rin", "form_id": "05000855|ccvsvsse004-beafarmer.esl", "type": "NPC_ FULL", "editor_id": "ccVSVSSE004_GhostChild", "string": "Рин"}, {"original": "Jonquil", "form_id": "0500085A|ccvsvsse004-beafarmer.esl", "type": "NPC_ FULL", "editor_id": "ccVSVSSE004_Wife", "string": "Джонкиль"}, {"original": "Ghost", "form_id": "0500085C|ccvsvsse004-beafarmer.esl", "type": "NPC_ FULL", "editor_id": "ccVSVSSE004_GhostWife_peaceful", "string": "Призрак"}, {"original": "Urval", "form_id": "05000859|ccvsvsse004-beafarmer.esl", "type": "NPC_ FULL", "editor_id": "ccVSVSSE004_Husband", "string": "Урваль"}, {"original": "Ghost", "form_id": "05000856|ccvsvsse004-beafarmer.esl", "type": "NPC_ FULL", "editor_id": "ccVSVSSE004_GhostWife", "string": "Призрак"}, {"original": "Ghost", "form_id": "05000857|ccvsvsse004-beafarmer.esl", "type": "NPC_ FULL", "editor_id": "ccVSVSSE004_GhostHusband", "string": "Призрак"}, {"original": "Child's Skeleton", "form_id": "05000858|ccvsvsse004-beafarmer.esl", "type": "NPC_ FULL", "editor_id": "ccVSVSSE004_ChildSkeleton", "string": "Скелет ребенка"}, {"original": "Key to Goldenhills Plantation", "form_id": "0500085D|ccvsvsse004-beafarmer.esl", "type": "KEYM FULL", "editor_id": "ccVSVSSE004_KEY_Farmhouse", "string": "Ключ от плантации \"Золотые холмы\""}, {"original": "Goldenhills Farm Bunkhouse", "form_id": "010030EB|Update.esm", "type": "CELL FULL", "editor_id": "ccVSVSSE004BunkhouseInterior", "string": "Ночлежка плантации \"Золотые холмы\""}, {"original": "Goldenhills Plantation", "form_id": "010030EC|Update.esm", "type": "CELL FULL", "editor_id": "ccVSVSSE004FarmhouseInterior", "string": "Плантация \"Золотые холмы\""}, {"original": "Marker Storage Unit", "form_id": "05000B20|ccvsvsse004-beafarmer.esl", "type": "CELL FULL", "editor_id": "ccVSVSSE004RefCell", "string": "Marker Storage Unit"}, {"original": "Skyrim", "form_id": "0000003C|Skyrim.esm", "type": "WRLD FULL", "editor_id": "Tamriel", "string": "Скайрим"}, {"original": "Goldenhills Plantation", "form_id": "05000B63|ccvsvsse004-beafarmer.esl", "type": "REFR FULL", "editor_id": "MapMarkerFarm", "string": "Плантация \"Золотые холмы\""}, {"original": "Stay here and guard the farm!", "form_id": "020154A4|Dawnguard.esm", "type": "INFO RNAM", "string": "Оставайся здесь и охраняй ферму!"}, {"original": "Stop guarding the farm.", "form_id": "05000CB5|ccvsvsse004-beafarmer.esl", "type": "INFO RNAM", "string": "Перестань охранять ферму."}, {"original": "I'd like you to purchase a horse for me. (<Global=VSVGLO_Horse> gold)", "form_id": "05000820|ccvsvsse004-beafarmer.esl", "type": "DIAL FULL", "editor_id": "ccVSVSSE004PurchaseHorseBranchTopic", "string": "Мне бы хотелось купить коня. (<Global=VSVGLO_Horse> зол.)"}, {"original": "Stay here and guard the farm!", "form_id": "05000CFF|ccvsvsse004-beafarmer.esl", "type": "DIAL FULL", "editor_id": "ccVSVSSE004GuardDogHireTopic", "string": "Оставайся здесь и охраняй ферму!"}, {"original": "(grunt)", "form_id": "05000D00|ccvsvsse004-beafarmer.esl", "type": "INFO NAM1", "index": 1, "string": "(ворчание)"}, {"original": "(grunt)", "form_id": "0500087B|ccvsvsse004-beafarmer.esl", "type": "INFO NAM1", "index": 1, "string": "(ворчание)"}, {"original": "Stop guarding the farm.", "form_id": "05000D01|ccvsvsse004-beafarmer.esl", "type": "DIAL FULL", "editor_id": "ccVSVSSE004GuardDogDismissTopic", "string": "Перестань охранять ферму."}, {"original": "(whine)", "form_id": "05000D02|ccvsvsse004-beafarmer.esl", "type": "INFO NAM1", "index": 1, "string": "(скулеж)"}, {"original": "Your family can rest in peace now.", "form_id": "05000D03|ccvsvsse004-beafarmer.esl", "type": "DIAL FULL", "editor_id": "VSMainQuest_FoundYourSonTopic", "string": "Твоя семья наконец обретет покой."}, {"original": "Your family can rest in peace now.", "form_id": "05000D04|ccvsvsse004-beafarmer.esl", "type": "INFO RNAM", "string": "Твоя семья наконец обретет покой."}, {"original": "Are there any problems around town that need handling?", "form_id": "05000D05|ccvsvsse004-beafarmer.esl", "type": "DIAL FULL", "editor_id": "VSMainQuest_BountyNoteTopic", "string": "В окрестностях города есть какие-то проблемы?"}, {"original": "I'm looking to hire a steward for my plantation. Interested?", "form_id": "05000D07|ccvsvsse004-beafarmer.esl", "type": "DIAL FULL", "editor_id": "ccVSVSSE004OverseerHireBranchTopic", "string": "Я ищу управляющего на ферму. Интересует такая работа?"}, {"original": "Would you be willing to act as steward for the plantation?", "form_id": "05000E91|ccvsvsse004-beafarmer.esl", "type": "INFO RNAM", "string": "Ты не хочешь побыть управляющим на этой плантации?"}, {"original": "Your services as steward are no longer required.", "form_id": "05000D09|ccvsvsse004-beafarmer.esl", "type": "DIAL FULL", "editor_id": "ccVSVSSE004OverseerDismissBranchTopic", "string": "Твои услуги мне больше не нужны."}, {"original": "My love, I don't need you to work as steward any more.", "form_id": "05000E92|ccvsvsse004-beafarmer.esl", "type": "INFO RNAM", "string": "Любовь моя, тебе больше не нужно работать на этой плантации."}, {"original": "I'd like you to buy new furnishings for the farmhouse.", "form_id": "05000D0B|ccvsvsse004-beafarmer.esl", "type": "DIAL FULL", "editor_id": "ccVSVSSE004UpgradeHouseBranchTopic", "string": "Мне бы хотелось купить обстановку для фермерского дома."}, {"original": "Kitchen. (<Global=VSVGLO_Kitchen> gold)", "form_id": "05000D0D|ccvsvsse004-beafarmer.esl", "type": "DIAL FULL", "editor_id": "ccVSVSSE004UpgradeKitchen", "string": "Кухня. (<Global=VSVGLO_Kitchen> зол.)"}, {"original": "Never mind.", "form_id": "05000D12|ccvsvsse004-beafarmer.esl", "type": "DIAL FULL", "editor_id": "ccVSVSSE004Nevermind", "string": "Уже не нужно."}, {"original": "Dining area. (<Global=VSVGLO_Dining> gold)", "form_id": "05000D15|ccvsvsse004-beafarmer.esl", "type": "DIAL FULL", "editor_id": "ccVSVSSE004UpgradeDining", "string": "Столовая. (<Global=VSVGLO_Kitchen> зол.)"}, {"original": "Alchemy and enchanting lab. (<Global=VSVGLO_Lab> gold)", "form_id": "05000D18|ccvsvsse004-beafarmer.esl", "type": "DIAL FULL", "editor_id": "ccVSVSSE004UpgradeLaboratory", "string": "Лаборатория для алхимии и зачарования. (<Global=VSVGLO_Lab> зол.)"}, {"original": "Loft. (<Global=VSVGLO_Loft> gold)", "form_id": "05000D1B|ccvsvsse004-beafarmer.esl", "type": "DIAL FULL", "editor_id": "ccVSVSSE004UpgradeLoft", "string": "Гостиная. (<Global=VSVGLO_Loft> зол.)"}, {"original": "Master bedroom. (<Global=VSVGLO_Bedroom> gold)", "form_id": "05000D1E|ccvsvsse004-beafarmer.esl", "type": "DIAL FULL", "editor_id": "ccVSVSSE004UpgradeBedroom", "string": "Хозяйская спальная. (<Global=VSVGLO_Bedroom> зол.)"}, {"original": "Child's bedroom. (<Global=VSVGLO_KidRoom> gold)", "form_id": "05000D21|ccvsvsse004-beafarmer.esl", "type": "DIAL FULL", "editor_id": "ccVSVSSE004UpgradeKidRoom", "string": "Детская. (<Global=VSVGLO_KidRoom> зол.)"}, {"original": "Replace my library room with a child's bedroom. (<Global=VSVGLO_KidRoom> gold)", "form_id": "05000D23|ccvsvsse004-beafarmer.esl", "type": "INFO RNAM", "string": "Заменить библиотеку на детскую. (<Global=VSVGLO_KidRoom> зол.)"}, {"original": "Replace my library room with a child's bedroom. (<Global=VSVGLO_KidRoom> gold)", "form_id": "05000FD4|ccvsvsse004-beafarmer.esl", "type": "INFO RNAM", "string": "Заменить библиотеку на детскую. (<Global=VSVGLO_KidRoom> зол.)"}, {"original": "Library and display room. (<Global=VSVGLO_KidRoomAlt> gold)", "form_id": "05000D25|ccvsvsse004-beafarmer.esl", "type": "DIAL FULL", "editor_id": "ccVSVSSE004UpgradeAltKidRoom", "string": "Библиотека и музей. (<Global=VSVGLO_KidRoomAlt> зол.)"}, {"original": "I'd like you to purchase livestock for the plantation.", "form_id": "05000E94|ccvsvsse004-beafarmer.esl", "type": "DIAL FULL", "editor_id": "ccVSVSSE004PurchaseAnimalsTopic", "string": "Мне бы хотелось закупить скот для этой плантации."}, {"original": "Never mind.", "form_id": "05000E98|ccvsvsse004-beafarmer.esl", "type": "DIAL FULL", "editor_id": "ccVSVSSE004PurchaseNevermindTopic", "string": "Уже не нужно."}, {"original": "A cow. (<Global=VSVGLO_AnimCow> gold)", "form_id": "05000E9B|ccvsvsse004-beafarmer.esl", "type": "DIAL FULL", "editor_id": "ccVSVSSE004PurchaseCowTopic", "string": "Корову. (<Global=VSVGLO_AnimCow> зол.)"}, {"original": "A few goats. (<Global=VSVGLO_AnimGoat> gold)", "form_id": "05000EA0|ccvsvsse004-beafarmer.esl", "type": "DIAL FULL", "editor_id": "ccVSVSSE004PurchaseGoats", "string": "Несколько коз. (<Global=VSVGLO_AnimGoat> зол.)"}, {"original": "A couple of chickens. (<Global=VSVGLO_AnimChick> gold)", "form_id": "05000EA3|ccvsvsse004-beafarmer.esl", "type": "DIAL FULL", "editor_id": "ccVSVSSE004PurchaseChickens", "string": "Пару кур. (<Global=VSVGLO_AnimChick> зол.)"}, {"original": "On second thought, I don't think I have enough gold right now.", "form_id": "05000FD8|ccvsvsse004-beafarmer.esl", "type": "INFO RNAM", "string": "Нет, все-таки сейчас у меня не так много золота."}, {"original": "I need you to hire some farmhands to work the farm. (<Global=VSVGLO_FHS> gold)", "form_id": "05000EA6|ccvsvsse004-beafarmer.esl", "type": "DIAL FULL", "editor_id": "ccVSVSSE004SpawnFarmhandBranchTopic", "string": "По-моему, пора нанять работников на ферму. (<Global=VSVGLO_FHS> зол.)"}, {"original": "I need you to hire another farmhand. (<Global=VSVGLO_FH> gold)", "form_id": "05000EA9|ccvsvsse004-beafarmer.esl", "type": "INFO RNAM", "string": "Кажется, пора нанять еще одного работника. (<Global=VSVGLO_FH> зол.)"}, {"original": "I need you to hire another farmhand. (<Global=VSVGLO_FH> gold)", "form_id": "05000FCE|ccvsvsse004-beafarmer.esl", "type": "INFO RNAM", "string": "Кажется, пора нанять еще одного работника. (<Global=VSVGLO_FH> зол.)"}, {"original": "I'm looking to hire a farmhand for my plantation. Interested?", "form_id": "05000EAB|ccvsvsse004-beafarmer.esl", "type": "DIAL FULL", "editor_id": "ccVSVSSE004FarmhandRecruitBranchTopic", "string": "Я ищу работника на свою ферму. Интересует такая работа?"}, {"original": "I can pay you <Global=VSVGLO_FH> gold.", "form_id": "05000EAD|ccvsvsse004-beafarmer.esl", "type": "DIAL FULL", "editor_id": "ccVSVSSE004OfferMoney", "string": "Могу заплатить <Global=VSVGLO_FH> зол."}, {"original": "On second thought, I seem to be short on coin...", "form_id": "05000EAF|ccvsvsse004-beafarmer.esl", "type": "INFO RNAM", "string": "Нет, все-таки у меня не так много денег."}, {"original": "I'm here to collect the plantation's profits.", "form_id": "05000EB0|ccvsvsse004-beafarmer.esl", "type": "DIAL FULL", "editor_id": "ccVSVSSE004CollectProfitBranchTopic", "string": "Я хочу забрать прибыль, принесенную плантацией."}, {"original": "You've done well running the plantation. Have we made any money?", "form_id": "05000EB3|ccvsvsse004-beafarmer.esl", "type": "INFO RNAM", "string": "Ты хорошо управляешь плантацией. От нее уже есть какая-то прибыль?"}, {"original": "Your services are no longer required.", "form_id": "05000EB4|ccvsvsse004-beafarmer.esl", "type": "DIAL FULL", "editor_id": "ccVSVSSE004FarmhandDismissBranchTopic", "string": "Твои услуги больше не нужны."}, {"original": "Speak to the innkepper at <Alias=InnRorikstead> or <Alias=InnWhiterun>", "form_id": "05000850|ccvsvsse004-beafarmer.esl", "type": "QUST NNAM", "index": 0, "editor_id": "ccVSVSSE004_IntroQuestMisc", "string": "Поговорить с хозяином трактира \"<Alias=InnRorikstead>\" или \"<Alias=InnWhiterun>\""}, {"original": "The Unquiet Dead", "form_id": "05000D28|ccvsvsse004-beafarmer.esl", "type": "QUST FULL", "editor_id": "ccVSVSSE004_MainQuest", "string": "Беспокойные мертвецы"}, {"original": "In Skyrim, talking to an innkeeper can provide you with jobs, rumors, and other interesting leads. I should speak with one and find out if they have anything I can help with.", "form_id": "05000D28|ccvsvsse004-beafarmer.esl", "type": "QUST CNAM", "index": 69, "editor_id": "ccVSVSSE004_MainQuest", "string": "В Скайриме трактирщик может дать работу, пересказать слухи и дать другие полезные сведения. Мне стоит поговорить с трактирщиком и узнать, чем я могу ему помочь."}, {"original": "<Alias=FarmLocation> near Rorikstead is reportedly haunted by ghosts that harass travelers on the road. The Jarl of Whiterun Hold is offering the plantation itself as a reward for anyone who can lay the spirits to rest. I should head to <Alias=FarmLocation> to investigate. ", "form_id": "05000D28|ccvsvsse004-beafarmer.esl", "type": "QUST CNAM", "index": 88, "editor_id": "ccVSVSSE004_MainQuest", "string": "По слухам, <Alias=FarmLocation> возле Рорикстеда представляет опасность: там появились призраки, которые нападают на проходящих мимо путников. Ярл Вайтрана готов отдать эту плантацию любому, кто очистит ее от беспокойных духов. Надо отправиться туда и узнать, в чем дело. "}, {"original": "Upon reaching <Alias=FarmLocation>, I discoverd that the rumors were true - this place is indeed haunted by the restless dead. What is driving the spirits of these simple farmers to such rage? And what sort of tragedy caused their untimely deaths? I should search the farm to find out more. ", "form_id": "05000D28|ccvsvsse004-beafarmer.esl", "type": "QUST CNAM", "index": 111, "editor_id": "ccVSVSSE004_MainQuest", "string": "Оказалось, что <Alias=FarmLocation> действительно опасное место, населенное неупокоенными мертвецами. Что же могло настолько разгневать простых фермеров? Какая трагедия привела к их безвременной гибели? Чтобы найти ответы, мне надо обыскать ферму. "}, {"original": "<Alias=Husband> accused his wife of being a witch before attacking her, after which she appears to have poisoned him. Could <Alias=Wife> have murdered her own son? I should try to find her secret laboratory to uncover the truth. ", "form_id": "05000D28|ccvsvsse004-beafarmer.esl", "type": "QUST CNAM", "index": 93, "editor_id": "ccVSVSSE004_MainQuest", "string": "Перед тем, как убить свою жену, <Alias=Husband> обвинил ее в том, что она ведьма. При этом она, кажется, успела его отравить. Может быть, <Alias=Wife> убила и собственного сына? Ответ на этот вопрос может скрываться в ее тайной лаборатории. "}, {"original": "<Alias=Wife> believed her angry, controlling husband had killed their son, <Alias=GhostChild>, so she poisoned him. Could <Alias=Husband> have murdered his own son? I should search the farm to find out more. ", "form_id": "05000D28|ccvsvsse004-beafarmer.esl", "type": "QUST CNAM", "index": 80, "editor_id": "ccVSVSSE004_MainQuest", "string": "<Alias=Wife> решила, что ее гневливый и деспотичный муж убил их общего ребенка, которого звали <Alias=GhostChild>. За это она отравила супруга. Неужели <Alias=Husband> и в самом деле прикончил собственного сына? Чтобы найти ответ на этот вопрос, надо обыскать ферму. "}, {"original": "I have uncovered the truth about what occurred at <Alias=FarmLocation>. After their son disappeared, <Alias=Husband> and <Alias=Wife> killed each other - <Alias=Wife> with extract of Deadly Nightshade, <Alias=Husband> with an axe - each thinking that the other had murdered their son, <Alias=GhostChild>. The only way to finally bring peace to their spirits is to discover what really became of <Alias=GhostChild>.", "form_id": "05000D28|ccvsvsse004-beafarmer.esl", "type": "QUST CNAM", "index": 83, "editor_id": "ccVSVSSE004_MainQuest", "string": "Мне удалось узнать, какую зловещую тайну скрывает <Alias=FarmLocation>. Когда пропал <Alias=GhostChild>, <Alias=Husband> и <Alias=Wife> обвинили друг друга в его убийстве, после чего <Alias=Wife> отравила мужа зельем из ядовитого паслена, а <Alias=Husband> зарубил ее топором. Чтобы вернуть покой их душам, мне надо выяснить, куда на самом деле подевался <Alias=GhostChild>."}, {"original": "I have uncovered the horrible truth about what occured at Goldenhills plantation. After their son disappeared, <Alias=Husband> and <Alias=Wife> killed each other, and their son appears to have run away to escape his parents' bickering. The only way to finally bring peace to the spirits here is to find out what happened to <Alias=GhostChild>, and to do that I need to find the old well mentioned in his journal.", "form_id": "05000D28|ccvsvsse004-beafarmer.esl", "type": "QUST CNAM", "index": 83, "editor_id": "ccVSVSSE004_MainQuest", "string": "Мне удалось узнать жуткую правду о том, что случилось на плантации \"Золотые холмы\". После исчезновения сына <Alias=Husband> и <Alias=Wife> убили друг друга, а сам сын, похоже, сбежал, устав от бесконечных ссор родителей. Чтобы вернуть покой душам фермеров, мне надо выяснить, куда на самом деле подевался <Alias=GhostChild>. В его дневнике упоминается старый колодец. Надо сходить туда."}, {"original": "I have found <Alias=GhostChild>'s remains near the old well, along with his beloved toy sword. According to his journal, he ran away from home to escape his parents' constant fighting; apparently, it looks like the wolves got the better of him. I should return the toy sword to <Alias=FarmLocation>, so that the spirits of <Alias=Husband> and <Alias=Wife> can finally know the truth of what happened to their son. ", "form_id": "05000D28|ccvsvsse004-beafarmer.esl", "type": "QUST CNAM", "index": 100, "editor_id": "ccVSVSSE004_MainQuest", "string": "Возле старого колодца мне удалось найти детский скелет с игрушечным мечом. Судя по всему, <Alias=GhostChild> сбежал туда от постоянных родительских ссор, а потом его задрали волки. Мне надо вернуть этот меч, чтобы <Alias=Husband> и<Alias=Wife> узнали о судьбе своего сына. Тогда <Alias=FarmLocation> наконец обретет покой. "}, {"original": "The restless spirits at <Alias=FarmLocation> can finally rest in peace, reunited with the spirit of their son and knowing that neither of them murdered their only child. Now that <Alias=FarmLocation> is no longer haunted, I can claim it for my own.", "form_id": "05000D28|ccvsvsse004-beafarmer.esl", "type": "QUST CNAM", "index": 63, "editor_id": "ccVSVSSE004_MainQuest", "string": "Теперь, когда духи погибших фермеров узнали правду и воссоединились со своим сыном, <Alias=FarmLocation> наконец обретет покой. Я же, в свою очередь, могу стать хозяином этих земель."}, {"original": "Ask an innkeeper for work", "form_id": "05000D28|ccvsvsse004-beafarmer.esl", "type": "QUST NNAM", "index": 0, "editor_id": "ccVSVSSE004_MainQuest", "string": "Спросить хозяина таверны насчет работы"}, {"original": "Travel to <Alias=FarmLocation>", "form_id": "05000D28|ccvsvsse004-beafarmer.esl", "type": "QUST NNAM", "index": 15, "editor_id": "ccVSVSSE004_MainQuest", "string": "Переместиться --> <Alias=FarmLocation>"}, {"original": "Search the plantation for clues", "form_id": "05000D28|ccvsvsse004-beafarmer.esl", "type": "QUST NNAM", "index": 50, "editor_id": "ccVSVSSE004_MainQuest", "string": "Обыскать плантацию в поисках зацепок"}, {"original": "Find the hidden laboratory", "form_id": "05000D28|ccvsvsse004-beafarmer.esl", "type": "QUST NNAM", "index": 61, "editor_id": "ccVSVSSE004_MainQuest", "string": "Найти тайную лабораторию"}, {"original": "Search the laboratory for clues", "form_id": "05000D28|ccvsvsse004-beafarmer.esl", "type": "QUST NNAM", "index": 65, "editor_id": "ccVSVSSE004_MainQuest", "string": "Обыскать лабораторию в поисках зацепок"}, {"original": "Find evidence of <Alias=Husband>'s guilt", "form_id": "05000D28|ccvsvsse004-beafarmer.esl", "type": "QUST NNAM", "index": 81, "editor_id": "ccVSVSSE004_MainQuest", "string": "Найти доказательства того, что <Alias=Husband> виновен"}, {"original": "Find out what happened to <Alias=GhostChild>", "form_id": "05000D28|ccvsvsse004-beafarmer.esl", "type": "QUST NNAM", "index": 100, "editor_id": "ccVSVSSE004_MainQuest", "string": "Выяснить, куда пропал <Alias=GhostChild>"}, {"original": "Find the old well", "form_id": "05000D28|ccvsvsse004-beafarmer.esl", "type": "QUST NNAM", "index": 102, "editor_id": "ccVSVSSE004_MainQuest", "string": "Найти старый колодец"}, {"original": "Take the toy sword", "form_id": "05000D28|ccvsvsse004-beafarmer.esl", "type": "QUST NNAM", "index": 103, "editor_id": "ccVSVSSE004_MainQuest", "string": "Взять игрушечный меч"}, {"original": "Return <Alias=GhostChild>'s toy sword to the farm", "form_id": "05000D28|ccvsvsse004-beafarmer.esl", "type": "QUST NNAM", "index": 200, "editor_id": "ccVSVSSE004_MainQuest", "string": "Вернуть на ферму игрушечный меч, который унес <Alias=GhostChild>"}, {"original": "Speak to <Alias=GhostChild>", "form_id": "05000D28|ccvsvsse004-beafarmer.esl", "type": "QUST NNAM", "index": 201, "editor_id": "ccVSVSSE004_MainQuest", "string": "<Alias=GhostChild> хочет со мной поговорить"}, {"original": "A Farmer's Life For Me", "form_id": "05000EB7|ccvsvsse004-beafarmer.esl", "type": "QUST FULL", "editor_id": "ccVSVSSE004_RestoreFarmQuest", "string": "Моя фермерская жизнь"}, {"original": "Now that I've laid the ghosts haunting <Alias=FarmLocation> to rest and claimed it for my own, I should see about getting my new homestead restored to its former glory. First I should get some crops in the ground.", "form_id": "05000EB7|ccvsvsse004-beafarmer.esl", "type": "QUST CNAM", "index": 87, "editor_id": "ccVSVSSE004_RestoreFarmQuest", "string": "Призраки обрели покой, а <Alias=FarmLocation> принадлежит мне. Пора заняться восстановлением моего нового дома. Для начала надо засеять поля."}, {"original": "I should find a steward to manage the day-to-day operations. Perhaps one of my allies would be willing to take on the job after I show them the place? Or I'm sure my spouse could run the farm, if I make this our home.", "form_id": "05000EB7|ccvsvsse004-beafarmer.esl", "type": "QUST CNAM", "index": 71, "editor_id": "ccVSVSSE004_RestoreFarmQuest", "string": "Повседневные дела фермы лучше всего доверить управляющему. Может быть, эту должность согласится занять кто-нибудь из моих союзников? А если мы сами поселимся здесь, руководство плантацией можно будет поручить моей второй половине."}, {"original": "I should find a steward to manage the day-to-day operations. Perhaps one of my allies would be willing to take on the job after I show them the place? Or if I were to get married, I could make this place our home and my spouse could run the farm.", "form_id": "05000EB7|ccvsvsse004-beafarmer.esl", "type": "QUST CNAM", "index": 90, "editor_id": "ccVSVSSE004_RestoreFarmQuest", "string": "Повседневные дела фермы лучше всего доверить управляющему. Может быть, эту должность согласится занять кто-нибудь из моих союзников? А если я все-таки заключу брак и поселюсь здесь, руководство плантацией можно будет поручить моей второй половине."}, {"original": "Now that I have a steward to manage the farm while I'm away, I should see about hiring some farmhands to tend to the crops and animals. I could either ask around in town to see if anyone is looking for work, or I could get my new steward to handle it. ", "form_id": "05000EB7|ccvsvsse004-beafarmer.esl", "type": "QUST CNAM", "index": 105, "editor_id": "ccVSVSSE004_RestoreFarmQuest", "string": "Теперь на ферме есть управляющий, чтобы следить за ее делами в мое отсутствие. Пора нанять работников, которые будут возделывать поля и ухаживать за скотом. Я могу поискать их в городе или доверить этот вопрос своему новому управляющему. "}, {"original": "<Alias=FarmLocation> is well on its way towards being a profitable farm again, now that I've planted crops and hired farmhands to tend to them. Next, I should see about acquiring some livestock. ", "form_id": "05000EB7|ccvsvsse004-beafarmer.esl", "type": "QUST CNAM", "index": 111, "editor_id": "ccVSVSSE004_RestoreFarmQuest", "string": "<Alias=FarmLocation> постепенно возвращается к прежнему виду. Поля снова засеяны, а наемные работники готовы на них трудиться. Пора завести скот. "}, {"original": "The crops are growing and the livestock are thriving. Soon I'll be able to start collecting the profit from my plantation. I should come back in a few days and speak to <Alias=Overseer> to collect what money has been earned. ", "form_id": "05000EB7|ccvsvsse004-beafarmer.esl", "type": "QUST CNAM", "index": 87, "editor_id": "ccVSVSSE004_RestoreFarmQuest", "string": "Поля зеленеют, скот процветает. Скоро моя плантация начнет приносить доход. Надо вернуться сюда через несколько дней: тогда <Alias=Overseer> сможет выдать мне полученную прибыль.  "}, {"original": "With <Alias=FarmLocation> thriving again, the excess crops and animal goods will be harvested by my hired help for my personal use. I should check the pantry inside the farmhouse to see what has been collected. ", "form_id": "05000EB7|ccvsvsse004-beafarmer.esl", "type": "QUST CNAM", "index": 94, "editor_id": "ccVSVSSE004_RestoreFarmQuest", "string": "<Alias=FarmLocation> снова процветает. Теперь работники будут откладывать излишки растительной и животной продукции для моих личных нужд. Я смогу найти их в кладовой своего фермерского дома. "}, {"original": "With <Alias=FarmLocation> thriving again, the excess crops and animal goods will be harvested by my hired help for my family's use. I should check the pantry inside the farmhouse to see what has been collected. ", "form_id": "05000EB7|ccvsvsse004-beafarmer.esl", "type": "QUST CNAM", "index": 84, "editor_id": "ccVSVSSE004_RestoreFarmQuest", "string": "<Alias=FarmLocation> снова процветает. Теперь работники будут откладывать излишки растительной и животной продукции для нужд моей семьи. Я смогу найти их в кладовой своего фермерского дома. "}, {"original": "I've returned <Alias=FarmLocation> to the thriving plantation it once was.", "form_id": "05000EB7|ccvsvsse004-beafarmer.esl", "type": "QUST CNAM", "index": 73, "editor_id": "ccVSVSSE004_RestoreFarmQuest", "string": "Благодаря мне <Alias=FarmLocation> снова процветает и приносит доход."}, {"original": "Plant crops (<Global=VSVGLO_CropsPlanted>/<Global=VSVGLO_CropsPlantedGoal>)", "form_id": "05000EB7|ccvsvsse004-beafarmer.esl", "type": "QUST NNAM", "index": 0, "editor_id": "ccVSVSSE004_RestoreFarmQuest", "string": "Засеять поля (<Global=VSVGLO_CropsPlanted>/<Global=VSVGLO_CropsPlantedGoal>)"}, {"original": "Hire a steward for the plantation", "form_id": "05000EB7|ccvsvsse004-beafarmer.esl", "type": "QUST NNAM", "index": 10, "editor_id": "ccVSVSSE004_RestoreFarmQuest", "string": "Нанять управляющего на ферму"}, {"original": "Recruit a farmhand to help with labor", "form_id": "05000EB7|ccvsvsse004-beafarmer.esl", "type": "QUST NNAM", "index": 20, "editor_id": "ccVSVSSE004_RestoreFarmQuest", "string": "Нанять работника на плантацию"}, {"original": "Build an animal pen", "form_id": "05000EB7|ccvsvsse004-beafarmer.esl", "type": "QUST NNAM", "index": 30, "editor_id": "ccVSVSSE004_RestoreFarmQuest", "string": "Построить загон для скота"}, {"original": "Talk to <Alias=Overseer> about purchasing livestock", "form_id": "05000EB7|ccvsvsse004-beafarmer.esl", "type": "QUST NNAM", "index": 40, "editor_id": "ccVSVSSE004_RestoreFarmQuest", "string": "<Alias=Overseer> может закупить скот для фермы"}, {"original": "Wait a few days for <Alias=FarmLocation> to start making money", "form_id": "05000EB7|ccvsvsse004-beafarmer.esl", "type": "QUST NNAM", "index": 50, "editor_id": "ccVSVSSE004_RestoreFarmQuest", "string": "Подождать несколько дней, пока <Alias=FarmLocation> не начнет приносить доход"}, {"original": "Talk to <Alias=Overseer> to collect the day's profit", "form_id": "05000EB7|ccvsvsse004-beafarmer.esl", "type": "QUST NNAM", "index": 60, "editor_id": "ccVSVSSE004_RestoreFarmQuest", "string": "<Alias=Overseer> может выдать вам дневную прибыль"}, {"original": "Collect the extra harvested produce from the pantry", "form_id": "05000EB7|ccvsvsse004-beafarmer.esl", "type": "QUST NNAM", "index": 70, "editor_id": "ccVSVSSE004_RestoreFarmQuest", "string": "Забрать излишки продукции из кладовой"}, {"original": "Collect Milk", "form_id": "05000EB9|ccvsvsse004-beafarmer.esl", "type": "PERK EPF2", "index": 1, "editor_id": "ccVSVSSE004_PERK_Player", "string": "Собрать молоко"}, {"original": "Remove Workbench", "form_id": "05000EB9|ccvsvsse004-beafarmer.esl", "type": "PERK EPF2", "index": 0, "editor_id": "ccVSVSSE004_PERK_Player", "string": "Убрать верстак"}, {"original": "Goldenhills Plantation", "form_id": "05000D36|ccvsvsse004-beafarmer.esl", "type": "LCTN FULL", "editor_id": "ccVSVSSE004_FarmExteriorLocation", "string": "Плантация \"Золотые холмы\""}, {"original": "Goldenhills Plantation", "form_id": "05000D37|ccvsvsse004-beafarmer.esl", "type": "LCTN FULL", "editor_id": "ccVSVSSE004_FarmInteriorLocation", "string": "Плантация \"Золотые холмы\""}, {"original": "Goldenhills Bunkhouse", "form_id": "05000D38|ccvsvsse004-beafarmer.esl", "type": "LCTN FULL", "editor_id": "ccVSVSSE004_BunkhouseInteriorLocation", "string": "Ночлежка плантации \"Золотые холмы\""}, {"original": "Choose a shrine to place here:", "form_id": "05000EBB|ccvsvsse004-beafarmer.esl", "type": "MESG DESC", "editor_id": "ccVSVSSE004_MSG_ChooseShrine2", "string": "Выберите святилище для размещения:"}, {"original": "(Prev)", "form_id": "05000EBB|ccvsvsse004-beafarmer.esl", "type": "MESG ITXT", "index": 0, "editor_id": "ccVSVSSE004_MSG_ChooseShrine2", "string": "(Назад)"}, {"original": "Julianos", "form_id": "05000EBB|ccvsvsse004-beafarmer.esl", "type": "MESG ITXT", "index": 1, "editor_id": "ccVSVSSE004_MSG_ChooseShrine2", "string": "Джулианос"}, {"original": "Kynareth", "form_id": "05000EBB|ccvsvsse004-beafarmer.esl", "type": "MESG ITXT", "index": 2, "editor_id": "ccVSVSSE004_MSG_ChooseShrine2", "string": "Кинарет"}, {"original": "Mara", "form_id": "05000EBB|ccvsvsse004-beafarmer.esl", "type": "MESG ITXT", "index": 3, "editor_id": "ccVSVSSE004_MSG_ChooseShrine2", "string": "Мара"}, {"original": "(Next)", "form_id": "05000EBB|ccvsvsse004-beafarmer.esl", "type": "MESG ITXT", "index": 4, "editor_id": "ccVSVSSE004_MSG_ChooseShrine2", "string": "(Далее)"}, {"original": "Farmhand <Alias=Farmhand2>", "form_id": "05000EC3|ccvsvsse004-beafarmer.esl", "type": "MESG FULL", "editor_id": "ccVSVSSE004_MSG_FarmhandName2", "string": "<Alias=Farmhand2> с фермы"}, {"original": "<Alias=Farmhand2> has left your employ.", "form_id": "05000D44|ccvsvsse004-beafarmer.esl", "type": "MESG DESC", "editor_id": "ccVSVSSE004_MSG_Farmhand2Dismiss", "string": "<Alias=Farmhand2> больше не работает на вас."}, {"original": "<Alias=GuardDog> is no longer guarding the farm.", "form_id": "05000EBF|ccvsvsse004-beafarmer.esl", "type": "MESG DESC", "editor_id": "ccVSVSSE004_MSG_GuardDogDismiss", "string": "<Alias=GuardDog> больше не охраняет ферму."}, {"original": "Your steward leaves your service.", "form_id": "05000D45|ccvsvsse004-beafarmer.esl", "type": "MESG DESC", "editor_id": "ccVSVSSE004_MSG_OverseerDismiss", "string": "Управляющий больше не служит вам."}, {"original": "Choose a shrine to place here:", "form_id": "05000EBA|ccvsvsse004-beafarmer.esl", "type": "MESG DESC", "editor_id": "ccVSVSSE004_MSG_ChooseShrine1", "string": "Выберите святилище для размещения:"}, {"original": "(Exit)", "form_id": "05000EBA|ccvsvsse004-beafarmer.esl", "type": "MESG ITXT", "index": 0, "editor_id": "ccVSVSSE004_MSG_ChooseShrine1", "string": "(Выход)"}, {"original": "Akatosh", "form_id": "05000EBA|ccvsvsse004-beafarmer.esl", "type": "MESG ITXT", "index": 1, "editor_id": "ccVSVSSE004_MSG_ChooseShrine1", "string": "Акатош"}, {"original": "Arkay", "form_id": "05000EBA|ccvsvsse004-beafarmer.esl", "type": "MESG ITXT", "index": 2, "editor_id": "ccVSVSSE004_MSG_ChooseShrine1", "string": "Аркей"}, {"original": "Dibella", "form_id": "05000EBA|ccvsvsse004-beafarmer.esl", "type": "MESG ITXT", "index": 3, "editor_id": "ccVSVSSE004_MSG_ChooseShrine1", "string": "Дибелла"}, {"original": "(Next)", "form_id": "05000EBA|ccvsvsse004-beafarmer.esl", "type": "MESG ITXT", "index": 4, "editor_id": "ccVSVSSE004_MSG_ChooseShrine1", "string": "(Далее)"}, {"original": "Choose a shrine to place here:", "form_id": "05000EBC|ccvsvsse004-beafarmer.esl", "type": "MESG DESC", "editor_id": "ccVSVSSE004_MSG_ChooseShrine3", "string": "Выберите святилище для размещения:"}, {"original": "(Prev)", "form_id": "05000EBC|ccvsvsse004-beafarmer.esl", "type": "MESG ITXT", "index": 0, "editor_id": "ccVSVSSE004_MSG_ChooseShrine3", "string": "(Назад)"}, {"original": "Stendarr", "form_id": "05000EBC|ccvsvsse004-beafarmer.esl", "type": "MESG ITXT", "index": 1, "editor_id": "ccVSVSSE004_MSG_ChooseShrine3", "string": "Стендарр"}, {"original": "Talos", "form_id": "05000EBC|ccvsvsse004-beafarmer.esl", "type": "MESG ITXT", "index": 2, "editor_id": "ccVSVSSE004_MSG_ChooseShrine3", "string": "Талос"}, {"original": "Zenithar", "form_id": "05000EBC|ccvsvsse004-beafarmer.esl", "type": "MESG ITXT", "index": 3, "editor_id": "ccVSVSSE004_MSG_ChooseShrine3", "string": "Зенитар"}, {"original": "(Next)", "form_id": "05000EBC|ccvsvsse004-beafarmer.esl", "type": "MESG ITXT", "index": 4, "editor_id": "ccVSVSSE004_MSG_ChooseShrine3", "string": "(Далее)"}, {"original": "Crops, milk, and eggs produced by the farm will be automatically stored in this cupboard. ", "form_id": "05000EC1|ccvsvsse004-beafarmer.esl", "type": "MESG DESC", "editor_id": "ccVSVSSE004_MSG_PantryCupboard", "string": "Зерно, молоко и яйца, произведенные на ферме, будут автоматически помещаться в буфет. "}, {"original": "Farmhand <Alias=Farmhand1>", "form_id": "05000EC2|ccvsvsse004-beafarmer.esl", "type": "MESG FULL", "editor_id": "ccVSVSSE004_MSG_FarmhandName1", "string": "<Alias=Farmhand1> с фермы"}, {"original": "Choose a shrine to place here:", "form_id": "05000EBE|ccvsvsse004-beafarmer.esl", "type": "MESG DESC", "editor_id": "ccVSVSSE004_MSG_ChooseShrine4", "string": "Выберите святилище для размещения:"}, {"original": "(Prev)", "form_id": "05000EBE|ccvsvsse004-beafarmer.esl", "type": "MESG ITXT", "index": 0, "editor_id": "ccVSVSSE004_MSG_ChooseShrine4", "string": "(Назад)"}, {"original": "Azura", "form_id": "05000EBE|ccvsvsse004-beafarmer.esl", "type": "MESG ITXT", "index": 1, "editor_id": "ccVSVSSE004_MSG_ChooseShrine4", "string": "Азура"}, {"original": "Boethiah", "form_id": "05000EBE|ccvsvsse004-beafarmer.esl", "type": "MESG ITXT", "index": 2, "editor_id": "ccVSVSSE004_MSG_ChooseShrine4", "string": "Боэтия"}, {"original": "Mephala", "form_id": "05000EBE|ccvsvsse004-beafarmer.esl", "type": "MESG ITXT", "index": 3, "editor_id": "ccVSVSSE004_MSG_ChooseShrine4", "string": "Мефала"}, {"original": "(Exit)", "form_id": "05000EBE|ccvsvsse004-beafarmer.esl", "type": "MESG ITXT", "index": 4, "editor_id": "ccVSVSSE004_MSG_ChooseShrine4", "string": "(Выход)"}, {"original": "Place the chosen shrine here? Once placed, the shrine cannot be changed. ", "form_id": "05000EBD|ccvsvsse004-beafarmer.esl", "type": "MESG DESC", "editor_id": "ccVSVSSE004_MSG_ChooseShrineConfirm", "string": "Поставить выбранное святилище здесь? После этого вы не сможете его изменить. "}, {"original": "Yes", "form_id": "05000EBD|ccvsvsse004-beafarmer.esl", "type": "MESG ITXT", "index": 0, "editor_id": "ccVSVSSE004_MSG_ChooseShrineConfirm", "string": "Да"}, {"original": "No", "form_id": "05000EBD|ccvsvsse004-beafarmer.esl", "type": "MESG ITXT", "index": 1, "editor_id": "ccVSVSSE004_MSG_ChooseShrineConfirm", "string": "Нет"}, {"original": "<Alias=Farmhand2> is now working for you.", "form_id": "05000D42|ccvsvsse004-beafarmer.esl", "type": "MESG DESC", "editor_id": "ccVSVSSE004_MSG_Farmhand2Hired", "string": "<Alias=Farmhand2> теперь работает на вас."}, {"original": "Permanently remove workbench?", "form_id": "05000EC0|ccvsvsse004-beafarmer.esl", "type": "MESG DESC", "editor_id": "ccVSVSSE004_MSG_WorkbenchRemoveConfirm", "string": "Убрать верстак навсегда?"}, {"original": "Yes", "form_id": "05000EC0|ccvsvsse004-beafarmer.esl", "type": "MESG ITXT", "index": 0, "editor_id": "ccVSVSSE004_MSG_WorkbenchRemoveConfirm", "string": "Да"}, {"original": "No", "form_id": "05000EC0|ccvsvsse004-beafarmer.esl", "type": "MESG ITXT", "index": 1, "editor_id": "ccVSVSSE004_MSG_WorkbenchRemoveConfirm", "string": "Нет"}, {"original": "<Alias=GuardDog> is now guarding the farm.", "form_id": "05000D40|ccvsvsse004-beafarmer.esl", "type": "MESG DESC", "editor_id": "ccVSVSSE004_MSG_GuardDogAssigned", "string": "<Alias=GuardDog> теперь охраняет ферму."}, {"original": "<Alias=GhostChild>'s Toy Sword", "form_id": "05000D3F|ccvsvsse004-beafarmer.esl", "type": "MESG FULL", "editor_id": "ccVSVSSE004_MSG_ToySwordName", "string": "Игрушечный меч, который унес <Alias=GhostChild>"}, {"original": "<Alias=Farmhand1> has left your employ.", "form_id": "05000D43|ccvsvsse004-beafarmer.esl", "type": "MESG DESC", "editor_id": "ccVSVSSE004_MSG_Farmhand1Dismiss", "string": "<Alias=Farmhand1> больше не работает на вас."}, {"original": "<Alias=Farmhand1> is now working for you.", "form_id": "05000D41|ccvsvsse004-beafarmer.esl", "type": "MESG DESC", "editor_id": "ccVSVSSE004_MSG_Farmhand1Hired", "string": "<Alias=Farmhand1> теперь работает на вас."}, {"original": "%.0f Quarried Stone added to workbench chest", "form_id": "05000FD9|ccvsvsse004-beafarmer.esl", "type": "MESG DESC", "editor_id": "ccVSVSSE004_MSG_SuppliesAddedStone", "string": "В сундук у верстака добавлен карьерный камень (%.0f)"}, {"original": "%.0f Straw added to workbench chest", "form_id": "05000FDA|ccvsvsse004-beafarmer.esl", "type": "MESG DESC", "editor_id": "ccVSVSSE004_MSG_SuppliesAddedStraw", "string": "В сундук у верстака добавлена солома (%.0f)"}, {"original": "%.0f Salt Pile added to farmhouse pantry", "form_id": "05000FDB|ccvsvsse004-beafarmer.esl", "type": "MESG DESC", "editor_id": "ccVSVSSE004_MSG_SuppliesAddedSalt", "string": "В кладовую фермы добавлена соль (%.0f)"}]